awkward_kaitai/__init__.py
awkward_kaitai/_version.py
awkward_kaitai/_version.pyi
awkward_kaitai/builder.py
awkward_kaitai/py.typed
awkward_kaitai/reader.py
awkward_kaitai/data/CMakeLists.txt
awkward_kaitai/data/__init__.py
awkward_kaitai/data/kaitai_struct_cpp_stl_runtime-CMakeLists.txt
awkward_kaitai-0.2.0.dist-info/METADATA
awkward_kaitai-0.2.0.dist-info/WHEEL
awkward_kaitai-0.2.0.dist-info/entry_points.txt
awkward_kaitai-0.2.0.dist-info/licenses/LICENSE
awkward_kaitai-0.2.0.dist-info/RECORD
