Metadata-Version: 2.3
Name: awkward_kaitai
Version: 0.2.0
Summary: Kaitai Struct runtime for Awkward Arrays
Project-URL: Homepage, https://github.com/ManasviGoyal/kaitai_struct_awkward_runtime
Project-URL: Bug Tracker, https://github.com/ManasviGoyal/kaitai_struct_awkward_runtime/issues
Project-URL: Discussions, https://github.com/ManasviGoyal/kaitai_struct_awkward_runtime/discussions
Project-URL: Changelog, https://github.com/ManasviGoyal/kaitai_struct_awkward_runtime/releases
Author-email: Manasvi Goyal <mg.manasvi@gmail.com>
Classifier: Development Status :: 1 - Planning
Classifier: Intended Audience :: Developers
Classifier: Intended Audience :: Science/Research
Classifier: License :: OSI Approved :: MIT License
Classifier: Operating System :: OS Independent
Classifier: Programming Language :: Python
Classifier: Programming Language :: Python :: 3
Classifier: Programming Language :: Python :: 3 :: Only
Classifier: Programming Language :: Python :: 3.8
Classifier: Programming Language :: Python :: 3.9
Classifier: Programming Language :: Python :: 3.10
Classifier: Programming Language :: Python :: 3.11
Classifier: Programming Language :: Python :: 3.12
Classifier: Topic :: Scientific/Engineering
Classifier: Typing :: Typed
Requires-Python: >=3.8
Requires-Dist: awkward>=2.6.5
Requires-Dist: importlib-resources
Provides-Extra: dev
Requires-Dist: pytest-cov>=3; extra == 'dev'
Requires-Dist: pytest>=6; extra == 'dev'
Provides-Extra: docs
Requires-Dist: mkdocs-material; extra == 'docs'
Provides-Extra: test
Requires-Dist: pytest-cov>=3; extra == 'test'
Requires-Dist: pytest>=6; extra == 'test'
